rak811v2/__init__.py
rak811v2/exception.py
rak811v2/rak811v2.py
rak811v2/serial.py
rak811v2-0.0.2.dist-info/LICENSE
rak811v2-0.0.2.dist-info/METADATA
rak811v2-0.0.2.dist-info/WHEEL
rak811v2-0.0.2.dist-info/top_level.txt
rak811v2-0.0.2.dist-info/RECORD
