Metadata-Version: 2.1
Name: rak811v2
Version: 0.0.2
Summary: Interface for RAK811 LoRa module
Home-page: https://github.com/teepbee/pyrak811v2
Author: Tim Brennan
Author-email: 80405873+teepbee@users.noreply.github.com
License: UNKNOWN
Platform: UNKNOWN
Classifier: Development Status :: 4 - Beta
Classifier: Intended Audience :: Developers
Classifier: Topic :: Software Development :: Libraries
Classifier: License :: OSI Approved :: Apache Software License
Classifier: Programming Language :: Python :: 3
Classifier: Operating System :: POSIX :: Linux
Requires-Python: >=3.5
Requires-Dist: pyserial
Requires-Dist: RPi.GPIO ; platform_machine == "armv7l" or platform_machine == "armv6l"
